PasswordProtectedHttpServer/__init__.py
PasswordProtectedHttpServer/__main__.py
PasswordProtectedHttpServer/src/server.py
passwordprotectedhttpserver-1.0.1.dist-info/LICENSE.txt
passwordprotectedhttpserver-1.0.1.dist-info/METADATA
passwordprotectedhttpserver-1.0.1.dist-info/WHEEL
passwordprotectedhttpserver-1.0.1.dist-info/RECORD
