Metadata-Version: 2.1
Name: PasswordProtectedHttpServer
Version: 1.0.1
Summary: CLI tool for running basic static websites with password protection
License: MIT
Author: marcelm9
Author-email: marcel.menzel09@gmail.com
Requires-Python: >=3.11,<4.0
Classifier: License :: OSI Approved :: MIT License
Classifier: Programming Language :: Python :: 3
Classifier: Programming Language :: Python :: 3.11
Classifier: Programming Language :: Python :: 3.12
Requires-Dist: flask (>=3.0.3,<4.0.0)
Requires-Dist: flask-jwt-extended (>=4.6.0,<5.0.0)
